<?xml version="1.0" encoding="utf-8"?>
<abapGit version="v1.0.0" serializer="LCL_OBJECT_VIEW" serializer_version="v1.0.0">
 <asx:abap xmlns:asx="http://www.sap.com/abapxml" version="1.0">
  <asx:values>
   <DD25V>
    <VIEWNAME>ZADOV_GRAINS_009</VIEWNAME>
    <AS4LOCAL>A</AS4LOCAL>
    <DDLANGUAGE>P</DDLANGUAGE>
    <AGGTYPE>V</AGGTYPE>
    <ROOTTAB>ZADOT_GRAINS_009</ROOTTAB>
    <DDTEXT>Visão - Configurações Grains - Usuários x Grp Autorização</DDTEXT>
    <VIEWCLASS>C</VIEWCLASS>
    <CUSTOMAUTH>A</CUSTOMAUTH>
    <GLOBALFLAG>X</GLOBALFLAG>
   </DD25V>
   <DD26V_TABLE>
    <DD26V>
     <VIEWNAME>ZADOV_GRAINS_009</VIEWNAME>
     <TABNAME>ZADOT_GRAINS_009</TABNAME>
     <TABPOS>0001</TABPOS>
     <FORTABNAME>ZADOT_GRAINS_009</FORTABNAME>
    </DD26V>
    <DD26V>
     <VIEWNAME>ZADOV_GRAINS_009</VIEWNAME>
     <TABNAME>ZADOT_GRAINS_008</TABNAME>
     <TABPOS>0002</TABPOS>
     <FORTABNAME>ZADOT_GRAINS_009</FORTABNAME>
     <FORFIELD>COMPANY_CODE</FORFIELD>
     <FORDIR>E</FORDIR>
    </DD26V>
    <DD26V>
     <VIEWNAME>ZADOV_GRAINS_009</VIEWNAME>
     <TABNAME>ZADOT_GRAINS_001</TABNAME>
     <TABPOS>0003</TABPOS>
     <FORTABNAME>ZADOT_GRAINS_008</FORTABNAME>
     <FORFIELD>COMPANY_CODE</FORFIELD>
     <FORDIR>E</FORDIR>
    </DD26V>
    <DD26V>
     <VIEWNAME>ZADOV_GRAINS_009</VIEWNAME>
     <TABNAME>T001</TABNAME>
     <TABPOS>0004</TABPOS>
     <FORTABNAME>ZADOT_GRAINS_001</FORTABNAME>
     <FORFIELD>COMPANY_CODE</FORFIELD>
     <FORDIR>E</FORDIR>
    </DD26V>
    <DD26V>
     <VIEWNAME>ZADOV_GRAINS_009</VIEWNAME>
     <TABNAME>USR21</TABNAME>
     <TABPOS>0005</TABPOS>
     <FORTABNAME>ZADOT_GRAINS_008</FORTABNAME>
     <FORFIELD>USERNAME</FORFIELD>
     <FORDIR>E</FORDIR>
    </DD26V>
    <DD26V>
     <VIEWNAME>ZADOV_GRAINS_009</VIEWNAME>
     <TABNAME>ADRP</TABNAME>
     <TABPOS>0006</TABPOS>
     <FORTABNAME>USR21</FORTABNAME>
     <FORFIELD>PERSNUMBER</FORFIELD>
     <FORDIR>E</FORDIR>
    </DD26V>
   </DD26V_TABLE>
   <DD27P_TABLE>
    <DD27P>
     <VIEWFIELD>MANDT</VIEWFIELD>
     <TABNAME>ZADOT_GRAINS_009</TABNAME>
     <FIELDNAME>MANDT</FIELDNAME>
     <KEYFLAG>X</KEYFLAG>
    </DD27P>
    <DD27P>
     <VIEWFIELD>COMPANY_CODE</VIEWFIELD>
     <TABNAME>ZADOT_GRAINS_009</TABNAME>
     <FIELDNAME>COMPANY_CODE</FIELDNAME>
     <KEYFLAG>X</KEYFLAG>
     <RDONLY>S</RDONLY>
     <CHECKTABLE>ZADOT_GRAINS_008</CHECKTABLE>
     <SHLPORIGIN>P</SHLPORIGIN>
     <SHLPNAME>C_T001</SHLPNAME>
     <SHLPFIELD>BUKRS</SHLPFIELD>
     <LOGFLAG>X</LOGFLAG>
    </DD27P>
    <DD27P>
     <VIEWFIELD>USERNAME</VIEWFIELD>
     <TABNAME>ZADOT_GRAINS_009</TABNAME>
     <FIELDNAME>USERNAME</FIELDNAME>
     <KEYFLAG>X</KEYFLAG>
     <RDONLY>S</RDONLY>
     <CHECKTABLE>ZADOT_GRAINS_008</CHECKTABLE>
     <SHLPORIGIN>P</SHLPORIGIN>
    </DD27P>
    <DD27P>
     <VIEWFIELD>AUTH_GROUP</VIEWFIELD>
     <TABNAME>ZADOT_GRAINS_009</TABNAME>
     <FIELDNAME>AUTH_GROUP</FIELDNAME>
     <KEYFLAG>X</KEYFLAG>
     <SHLPORIGIN>F</SHLPORIGIN>
     <VALEXI>X</VALEXI>
    </DD27P>
    <DD27P>
     <VIEWFIELD>ACTIVE</VIEWFIELD>
     <TABNAME>ZADOT_GRAINS_009</TABNAME>
     <FIELDNAME>ACTIVE</FIELDNAME>
     <SHLPORIGIN>F</SHLPORIGIN>
     <VALEXI>X</VALEXI>
    </DD27P>
    <DD27P>
     <VIEWFIELD>COMPANY_CODE_DESCR</VIEWFIELD>
     <TABNAME>T001</TABNAME>
     <FIELDNAME>BUTXT</FIELDNAME>
     <RDONLY>H</RDONLY>
    </DD27P>
    <DD27P>
     <VIEWFIELD>NAME_TEXT</VIEWFIELD>
     <TABNAME>ADRP</TABNAME>
     <FIELDNAME>NAME_TEXT</FIELDNAME>
     <RDONLY>H</RDONLY>
    </DD27P>
   </DD27P_TABLE>
   <DD28J_TABLE>
    <DD28J>
     <VIEWNAME>ZADOV_GRAINS_009</VIEWNAME>
     <LTAB>ZADOT_GRAINS_008</LTAB>
     <LFIELD>MANDT</LFIELD>
     <OPERATOR>EQ</OPERATOR>
     <RTAB>ZADOT_GRAINS_009</RTAB>
     <RFIELD>MANDT</RFIELD>
     <SOURCE>F</SOURCE>
     <FRKTAB>ZADOT_GRAINS_009</FRKTAB>
     <FRKFIELD>COMPANY_CODE</FRKFIELD>
     <FRKDIR>E</FRKDIR>
    </DD28J>
    <DD28J>
     <VIEWNAME>ZADOV_GRAINS_009</VIEWNAME>
     <LTAB>ZADOT_GRAINS_008</LTAB>
     <LFIELD>COMPANY_CODE</LFIELD>
     <OPERATOR>EQ</OPERATOR>
     <RTAB>ZADOT_GRAINS_009</RTAB>
     <RFIELD>COMPANY_CODE</RFIELD>
     <SOURCE>F</SOURCE>
     <FRKTAB>ZADOT_GRAINS_009</FRKTAB>
     <FRKFIELD>COMPANY_CODE</FRKFIELD>
     <FRKDIR>E</FRKDIR>
    </DD28J>
    <DD28J>
     <VIEWNAME>ZADOV_GRAINS_009</VIEWNAME>
     <LTAB>ZADOT_GRAINS_008</LTAB>
     <LFIELD>USERNAME</LFIELD>
     <OPERATOR>EQ</OPERATOR>
     <RTAB>ZADOT_GRAINS_009</RTAB>
     <RFIELD>USERNAME</RFIELD>
     <SOURCE>F</SOURCE>
     <FRKTAB>ZADOT_GRAINS_009</FRKTAB>
     <FRKFIELD>COMPANY_CODE</FRKFIELD>
     <FRKDIR>E</FRKDIR>
    </DD28J>
    <DD28J>
     <VIEWNAME>ZADOV_GRAINS_009</VIEWNAME>
     <LTAB>ZADOT_GRAINS_001</LTAB>
     <LFIELD>MANDT</LFIELD>
     <OPERATOR>EQ</OPERATOR>
     <RTAB>ZADOT_GRAINS_008</RTAB>
     <RFIELD>MANDT</RFIELD>
     <SOURCE>F</SOURCE>
     <FRKTAB>ZADOT_GRAINS_008</FRKTAB>
     <FRKFIELD>COMPANY_CODE</FRKFIELD>
     <FRKDIR>E</FRKDIR>
    </DD28J>
    <DD28J>
     <VIEWNAME>ZADOV_GRAINS_009</VIEWNAME>
     <LTAB>ZADOT_GRAINS_001</LTAB>
     <LFIELD>COMPANY_CODE</LFIELD>
     <OPERATOR>EQ</OPERATOR>
     <RTAB>ZADOT_GRAINS_008</RTAB>
     <RFIELD>COMPANY_CODE</RFIELD>
     <SOURCE>F</SOURCE>
     <FRKTAB>ZADOT_GRAINS_008</FRKTAB>
     <FRKFIELD>COMPANY_CODE</FRKFIELD>
     <FRKDIR>E</FRKDIR>
    </DD28J>
    <DD28J>
     <VIEWNAME>ZADOV_GRAINS_009</VIEWNAME>
     <LTAB>T001</LTAB>
     <LFIELD>MANDT</LFIELD>
     <OPERATOR>EQ</OPERATOR>
     <RTAB>ZADOT_GRAINS_001</RTAB>
     <RFIELD>MANDT</RFIELD>
     <SOURCE>F</SOURCE>
     <FRKTAB>ZADOT_GRAINS_001</FRKTAB>
     <FRKFIELD>COMPANY_CODE</FRKFIELD>
     <FRKDIR>E</FRKDIR>
    </DD28J>
    <DD28J>
     <VIEWNAME>ZADOV_GRAINS_009</VIEWNAME>
     <LTAB>T001</LTAB>
     <LFIELD>BUKRS</LFIELD>
     <OPERATOR>EQ</OPERATOR>
     <RTAB>ZADOT_GRAINS_001</RTAB>
     <RFIELD>COMPANY_CODE</RFIELD>
     <SOURCE>F</SOURCE>
     <FRKTAB>ZADOT_GRAINS_001</FRKTAB>
     <FRKFIELD>COMPANY_CODE</FRKFIELD>
     <FRKDIR>E</FRKDIR>
    </DD28J>
    <DD28J>
     <VIEWNAME>ZADOV_GRAINS_009</VIEWNAME>
     <LTAB>USR21</LTAB>
     <LFIELD>MANDT</LFIELD>
     <OPERATOR>EQ</OPERATOR>
     <RTAB>ZADOT_GRAINS_008</RTAB>
     <RFIELD>MANDT</RFIELD>
     <SOURCE>F</SOURCE>
     <FRKTAB>ZADOT_GRAINS_008</FRKTAB>
     <FRKFIELD>USERNAME</FRKFIELD>
     <FRKDIR>E</FRKDIR>
    </DD28J>
    <DD28J>
     <VIEWNAME>ZADOV_GRAINS_009</VIEWNAME>
     <LTAB>USR21</LTAB>
     <LFIELD>BNAME</LFIELD>
     <OPERATOR>EQ</OPERATOR>
     <RTAB>ZADOT_GRAINS_008</RTAB>
     <RFIELD>USERNAME</RFIELD>
     <SOURCE>F</SOURCE>
     <FRKTAB>ZADOT_GRAINS_008</FRKTAB>
     <FRKFIELD>USERNAME</FRKFIELD>
     <FRKDIR>E</FRKDIR>
    </DD28J>
    <DD28J>
     <VIEWNAME>ZADOV_GRAINS_009</VIEWNAME>
     <LTAB>ADRP</LTAB>
     <LFIELD>PERSNUMBER</LFIELD>
     <OPERATOR>EQ</OPERATOR>
     <RTAB>USR21</RTAB>
     <RFIELD>PERSNUMBER</RFIELD>
     <SOURCE>F</SOURCE>
     <FRKTAB>USR21</FRKTAB>
     <FRKFIELD>PERSNUMBER</FRKFIELD>
     <FRKDIR>E</FRKDIR>
    </DD28J>
   </DD28J_TABLE>
  </asx:values>
 </asx:abap>
</abapGit>
